tedpy/__init__.py
tedpy/__main__.py
tedpy/dataclasses.py
tedpy/formatting.py
tedpy/py.typed
tedpy/ted.py
tedpy/ted5000.py
tedpy/ted6000.py
tedpy-1.1.0.dist-info/METADATA
tedpy-1.1.0.dist-info/WHEEL
tedpy-1.1.0.dist-info/RECORD
