Metadata-Version: 2.1
Name: tedpy
Version: 1.1.0
Summary: Unofficial library for reading from The Energy Detective power meters
Home-page: https://github.com/rianadon/the-energy-detective-py
License: Apache-2.0
Author: rianadon
Requires-Python: >=3.7,<4.0
Classifier: License :: OSI Approved :: Apache Software License
Classifier: Programming Language :: Python :: 3
Classifier: Programming Language :: Python :: 3.7
Classifier: Programming Language :: Python :: 3.8
Classifier: Programming Language :: Python :: 3.9
Classifier: Programming Language :: Python :: 3.10
Classifier: Programming Language :: Python :: 3.11
Requires-Dist: httpx (>=0.20,<1.0)
Requires-Dist: xmltodict (>=0.12,<1.0)
Project-URL: Documentation, https://github.com/rianadon/the-energy-detective-py#readme
Project-URL: Repository, https://github.com/rianadon/the-energy-detective-py
